astromandala/__init__.py
astromandala/mandala.py
astromandala-0.0.5.dist-info/METADATA
astromandala-0.0.5.dist-info/WHEEL
astromandala-0.0.5.dist-info/top_level.txt
astromandala-0.0.5.dist-info/RECORD
