Metadata-Version: 2.1
Name: astromandala
Version: 0.0.5
Summary: Astrology Software
Home-page: https://astromandala.com
Author: Christoph Chester Cury
Author-email: cury.grupos@gmail.com
License: UNKNOWN
Project-URL: Bug Tracker, https://github.com/
Platform: UNKNOWN
Classifier: Programming Language :: Python :: 3
Classifier: License :: OSI Approved :: MIT License
Classifier: Operating System :: OS Independent
Requires-Python: >=3.6
